<includes>

	<include name="ShowcaseMediaFlagLightShade">
		<colordiffuse>74000000</colordiffuse>	
	</include>
	
	<include name="ShowcaseMediaFlagNightShade">
		<colordiffuse>FFe1e1e1</colordiffuse>	
	</include>

	<include name="Furniture_ShowcaseMediaFlagsVars">
		<posy>647</posy>
		<width>110</width>
		<height>72</height>
		<include>Animation_CommonFade</include>
		<include>Animation_HideShowcase</include>
		<visible>Control.IsVisible(57)</visible>
		<include condition="!Skin.HasSetting(darkshowcase)">ShowcaseMediaFlagLightShade</include>
		<include condition="Skin.HasSetting(darkshowcase)">ShowcaseMediaFlagNightShade</include>
	</include>
	
	<include name="Furniture_ListMediaFlagsVars">
		<posy>630</posy>
		<width>90</width>
		<height>59</height>
		<include>Animation_CommonFade</include>
		<include>Animation_HideShowcase</include>
		<visible>Control.IsVisible(50)</visible>
		<colordiffuse>74000000</colordiffuse>
	</include>	
	
	<include name="Furniture_PanelMediaFlagsVars">
		<posy>454</posy>
		<width>90</width>
		<height>59</height>
		<include>Animation_CommonFade</include>
		<visible>Control.IsVisible(52)</visible>		
	</include>	
	
	<include name="Furniture_ShowcaseMediaFlagsBlack">
		<posy>647</posy>
		<width>110</width>
		<height>72</height>
		<include>Animation_CommonFade</include>
		<include>Animation_HideShowcase</include>
		<include>Conditions_ShowcaseIsVisible</include>
	</include>

	<include name="Furniture_MovieInfoFlagSource">
		<posx>4</posx>
		<posy>589</posy>
		<width>93</width>
		<height>30</height>
		<colordiffuse>FF7c7c7c</colordiffuse>
	</include>

	<include name="Furniture_MovieInfoFlagSound">
		<posx>115</posx>
		<posy>589</posy>
		<width>131</width>
		<height>30</height>
		<colordiffuse>FF7c7c7c</colordiffuse>
		<animation effect="slide" start="-148,0" end="-148,0" time="0" condition="Control.IsVisible(91) + !Control.IsVisible(92)">Conditional</animation>
		<animation effect="slide" start="-111,0" end="-111,0" time="0" condition="!Control.IsVisible(91)">Conditional</animation>			
	</include>

	<include name="Furniture_MovieInfoFlagSubs">
		<posx>263</posx>
		<posy>589</posy>
		<width>39</width>
		<height>30</height>
		<colordiffuse>FF7c7c7c</colordiffuse>
		<animation effect="slide" start="-111,0" end="-111,0" time="0" condition="!Control.IsVisible(91) + Control.IsVisible(92)">Conditional</animation>		
		<animation effect="slide" start="-259,0" end="-259,0" time="0" condition="!Control.IsVisible(91) + !Control.IsVisible(92)">Conditional</animation>		
		<animation effect="slide" start="-148,0" end="-148,0" time="0" condition="Control.IsVisible(91) + !Control.IsVisible(92)">Conditional</animation>
	</include>

	<include name="Furniture_MovieInfoFlagRes">
		<posx>325</posx>
		<posy>589</posy>
		<width>67</width>
		<height>30</height>
		<colordiffuse>FF7c7c7c</colordiffuse>
		<animation effect="slide" start="-210,0" end="-210,0" time="0" condition="Control.IsVisible(91) + !Control.IsVisible(92) + !Control.IsVisible(93)">Conditional</animation>		
		<animation effect="slide" start="-147,0" end="-147,0" time="0" condition="Control.IsVisible(91) + !Control.IsVisible(92) + Control.IsVisible(93)">Conditional</animation>
		<animation effect="slide" start="-260,0" end="-260,0" time="0" condition="!Control.IsVisible(91) + !Control.IsVisible(92) + Control.IsVisible(93)">Conditional</animation>			
		<animation effect="slide" start="-110,0" end="-110,0" time="0" condition="!Control.IsVisible(91) + Control.IsVisible(92) + Control.IsVisible(93)">Conditional</animation>		
		<animation effect="slide" start="-173,0" end="-173,0" time="0" condition="!Control.IsVisible(91) + Control.IsVisible(92) + !Control.IsVisible(93)">Conditional</animation>			
		<animation effect="slide" start="-59,0" end="-59,0" time="0" condition="Control.IsVisible(91) + Control.IsVisible(92) + !Control.IsVisible(93)">Conditional</animation>		
		<animation effect="slide" start="-321,0" end="-321,0" time="0" condition="!Control.IsVisible(91) + !Control.IsVisible(92) + !Control.IsVisible(93) + Control.IsVisible(94)">Conditional</animation>		
	</include>	

	<include name="Furniture_FlagUpright">
		<posy>581</posy>		
		<width>1</width>
		<height>47</height>
		<texture>info/info_flagupright.png</texture>
		<animation effect="fade" start="70" end="70" time="0" condition="Skin.HasSetting(lite)">Conditional</animation>	
	</include>
	
	<include name="Furniture_MovieInfoMediaFlags">
	
		<control type="image">
			<posx>104</posx>
			<include>Furniture_FlagUpright</include>
			<visible>Control.IsVisible(91) + [Control.IsVisible(92) | Control.IsVisible(93) | Control.IsVisible(94) | Skin.HasSetting(inforatings)]</visible>
		</control>
		
		<control type="image">
			<posx>253</posx>
			<include>Furniture_FlagUpright</include>
			<visible>Control.IsVisible(92) + [Control.IsVisible(93) | Control.IsVisible(94) | Skin.HasSetting(inforatings)]</visible>
			<animation effect="slide" start="-111,0" end="-111,0" time="0" condition="!Control.IsVisible(91)">Conditional</animation>			
		</control>	

		<control type="image">
			<posx>313</posx>
			<include>Furniture_FlagUpright</include>
			<visible>Control.IsVisible(93) + [Control.IsVisible(94) | Skin.HasSetting(inforatings)]</visible>
			<animation effect="slide" start="-110,0" end="-110,0" time="0" condition="!Control.IsVisible(91) + Control.IsVisible(92) + Control.IsVisible(93)">Conditional</animation>			
			<animation effect="slide" start="-259,0" end="-259,0" time="0" condition="!Control.IsVisible(91) + !Control.IsVisible(92)">Conditional</animation>				
			<animation effect="slide" start="-148,0" end="-148,0" time="0" condition="Control.IsVisible(91) + !Control.IsVisible(92)">Conditional</animation>			
		</control>

		<control type="image">
			<posx>403</posx>
			<include>Furniture_FlagUpright</include>
			<visible>Control.IsVisible(94) + Skin.HasSetting(inforatings)</visible>
			<animation effect="slide" start="-110,0" end="-110,0" time="0" condition="!Control.IsVisible(91) + Control.IsVisible(92) + Control.IsVisible(93)">Conditional</animation>			
			<animation effect="slide" start="-259,0" end="-259,0" time="0" condition="!Control.IsVisible(91) + !Control.IsVisible(92)">Conditional</animation>				
			<animation effect="slide" start="-148,0" end="-148,0" time="0" condition="Control.IsVisible(91) + !Control.IsVisible(92) + Control.IsVisible(93)">Conditional</animation>			
			<animation effect="slide" start="-58,0" end="-58,0" time="0" condition="Control.IsVisible(91) + Control.IsVisible(92) + !Control.IsVisible(93)">Conditional</animation>			
			<animation effect="slide" start="-64,0" end="-64,0" time="0" condition="!Control.IsVisible(91) + !Control.IsVisible(92) + !Control.IsVisible(93)">Conditional</animation>			
			<animation effect="slide" start="-212,0" end="-212,0" time="0" condition="Control.IsVisible(91) + !Control.IsVisible(92) + !Control.IsVisible(93)">Conditional</animation>			
			<animation effect="slide" start="-175,0" end="-175,0" time="0" condition="!Control.IsVisible(91) + Control.IsVisible(92) + !Control.IsVisible(93)">Conditional</animation>				
		</control>		
	
		<control type="image" id="91">
			<include>Furniture_MovieInfoFlagSource</include>
			<texture>flags/info/bluray.png</texture>
			<visible>substring(listitem.filename,bluray) | substring(listitem.filename,blu-ray) | substring(listitem.filename,brrip)</visible>
		</control>
		
		<control type="image" id="91">
			<include>Furniture_MovieInfoFlagSource</include>
			<texture>flags/info/dvd.png</texture>
			<visible>substring(listitem.filename,sddvd) | substring(listitem.filename,dvdrip)</visible>
		</control>

		<control type="image" id="91">
			<include>Furniture_MovieInfoFlagSource</include>
			<texture>flags/info/hdtv.png</texture>
			<visible>substring(listitem.filename,hdtv)</visible>
		</control>

		<control type="image" id="91">
			<include>Furniture_MovieInfoFlagSource</include>
			<texture>flags/info/hddvd.png</texture>
			<visible>substring(listitem.filename,hddvd)</visible>
		</control>		

		<control type="image" id="92">
			<include>Furniture_MovieInfoFlagSound</include>
			<texture>flags/info/dd51.png</texture>
			<visible>substring(listitem.studio,6ch) + substring(listitem.studio,ac-3)</visible>
		</control>

		<control type="image" id="92">
			<include>Furniture_MovieInfoFlagSound</include>
			<texture>flags/info/dd71.png</texture>
			<visible>substring(listitem.studio,8ch) + substring(listitem.studio,ac-3)</visible>
		</control>

		<control type="image" id="92">
			<include>Furniture_MovieInfoFlagSound</include>
			<texture>flags/info/dts51.png</texture>
			<visible>substring(listitem.studio,6ch) + substring(listitem.studio,dts)</visible>
		</control>

		<control type="image" id="92">
			<include>Furniture_MovieInfoFlagSound</include>
			<texture>flags/info/dts71.png</texture>
			<visible>substring(listitem.studio,8ch) + substring(listitem.studio,dts)</visible>
		</control>

		<control type="image" id="92">
			<include>Furniture_MovieInfoFlagSound</include>
			<texture>flags/info/dolby20.png</texture>
			<visible>substring(listitem.studio,2ch)</visible>
		</control>

		<control type="image" id="92">
			<include>Furniture_MovieInfoFlagSound</include>
			<texture>flags/info/mono.png</texture>
			<visible>substring(listitem.studio,mono)</visible>
		</control>

		<control type="image" id="93">
			<include>Furniture_MovieInfoFlagSubs</include>
			<texture>flags/info/cc.png</texture>
			<visible>substring(listitem.studio,sub)</visible>
		</control>

		<control type="image" id="94">
			<include>Furniture_MovieInfoFlagRes</include>
			<texture>flags/info/480i.png</texture>
			<visible>substring(listitem.studio,480i)</visible>
		</control>

		<control type="image" id="94">
			<include>Furniture_MovieInfoFlagRes</include>
			<texture>flags/info/576i.png</texture>
			<visible>substring(listitem.studio,576i)</visible>
		</control>	

		<control type="image" id="94">
			<include>Furniture_MovieInfoFlagRes</include>
			<texture>flags/info/720i.png</texture>
			<visible>substring(listitem.studio,720i)</visible>
		</control>

		<control type="image" id="94">
			<include>Furniture_MovieInfoFlagRes</include>
			<texture>flags/info/1080i.png</texture>
			<visible>substring(listitem.studio,1080i)</visible>
		</control>

		<control type="image" id="94">
			<include>Furniture_MovieInfoFlagRes</include>
			<texture>flags/info/480p.png</texture>
			<visible>substring(listitem.studio,480p)</visible>
		</control>

		<control type="image" id="94">
			<include>Furniture_MovieInfoFlagRes</include>
			<texture>flags/info/576p.png</texture>
			<visible>substring(listitem.studio,576p)</visible>
		</control>	

		<control type="image" id="94">
			<include>Furniture_MovieInfoFlagRes</include>
			<texture>flags/info/720p.png</texture>
			<visible>substring(listitem.studio,720p)</visible>
		</control>

		<control type="image" id="94">
			<include>Furniture_MovieInfoFlagRes</include>
			<texture>flags/info/1080p.png</texture>
			<visible>substring(listitem.studio,1080p)</visible>
		</control>		
	</include>

	<include name="Furniture_ListMediaFlags">
		<visible>Control.IsVisible(50) + [Container.Content(movies) | Container.Content(episodes) | Container.Content(tvshows) | Container.Content(seasons)]</visible>
		<include>Animation_CommonFade</include>
			<control type="group">
				<posx>1105</posx>
				<control type="image">
					<include>Furniture_ListMediaFlagsVars</include>
					<texture>flags/defaultscreen.png</texture>
					<visible>!Control.IsVisible(187) + !Skin.HasSetting(nodefaultflags)</visible>
				</control>
				<control type="image" id="187">
					<include>Furniture_ListMediaFlagsVars</include>
					<texture>flags/sd.png</texture>
					<visible>substring(listitem.studio,sd)</visible>
				</control>
				<control type="image" id="187">
					<include>Furniture_ListMediaFlagsVars</include>
					<texture>flags/480p.png</texture>
					<visible>substring(listitem.studio,480p)</visible>
				</control>
				<control type="image" id="187">
					<include>Furniture_ListMediaFlagsVars</include>
					<texture>flags/576p.png</texture>
					<visible>substring(listitem.studio,576p)</visible>
				</control>				
				<control type="image" id="187">
					<include>Furniture_ListMediaFlagsVars</include>
					<texture>flags/720p.png</texture>
					<visible>substring(listitem.studio,720p)</visible>
				</control>
				<control type="image" id="187">
					<include>Furniture_ListMediaFlagsVars</include>
					<texture>flags/1080p.png</texture>
					<visible>substring(listitem.studio,1080p)</visible>
				</control>
				<control type="image" id="187">
					<include>Furniture_ListMediaFlagsVars</include>
					<texture>flags/480i.png</texture>
					<visible>substring(listitem.studio,480i)</visible>
				</control>
				<control type="image" id="187">
					<include>Furniture_ListMediaFlagsVars</include>
					<texture>flags/576i.png</texture>
					<visible>substring(listitem.studio,576i)</visible>
				</control>				
				<control type="image" id="187">
					<include>Furniture_ListMediaFlagsVars</include>
					<texture>flags/720i.png</texture>
					<visible>substring(listitem.studio,720i)</visible>
				</control>
				<control type="image" id="187">
					<include>Furniture_ListMediaFlagsVars</include>
					<texture>flags/1080i.png</texture>
					<visible>substring(listitem.studio,1080i)</visible>
				</control>				
			</control>
			<control type="group">
				<posx>981</posx>
				<control type="image">
					<include>Furniture_ListMediaFlagsVars</include>
					<texture>flags/defaultsound.png</texture>
					<visible>!Control.IsVisible(188) + !Skin.HasSetting(nodefaultflags)</visible>
				</control>					
				<control type="image" id="188">
					<include>Furniture_ListMediaFlagsVars</include>
					<texture>flags/dts.png</texture>
					<visible>substring(listitem.studio,dts) + !substring(listitem.studio,ac-3)</visible>
				</control>			
				<control type="image" id="188">
					<include>Furniture_ListMediaFlagsVars</include>
					<texture>flags/dolbydigital.png</texture>
					<visible>substring(listitem.studio,ac-3)</visible>
				</control>
				<control type="image" id="188">
					<include>Furniture_ListMediaFlagsVars</include>
					<texture>flags/mp3.png</texture>
					<visible>substring(listitem.studio,mp3) | substring(listitem.studio,MPEG Audio)</visible>
				</control>				
			</control>
			<control type="group">
				<posx>855</posx>
				<control type="image">
					<include>Furniture_ListMediaFlagsVars</include>
					<texture>flags/defaultsource.png</texture>
					<visible>!Control.IsVisible(189) + !Skin.HasSetting(nodefaultflags)</visible>
				</control>				
				<control type="image" id="189">
					<include>Furniture_ListMediaFlagsVars</include>
					<texture>flags/hddvd.png</texture>
					<visible>substring(listitem.filename,hddvd)</visible>
				</control>
				<control type="image" id="189">
					<include>Furniture_ListMediaFlagsVars</include>
					<texture>flags/bluray.png</texture>
					<visible>substring(listitem.filename,bluray)</visible>
				</control>
				<control type="image" id="189">
					<include>Furniture_ListMediaFlagsVars</include>
					<texture>flags/dvd.png</texture>
					<visible>substring(listitem.filename,sddvd)</visible>
				</control>
				<control type="image" id="189">
					<include>Furniture_ListMediaFlagsVars</include>
					<texture>flags/hdtv.png</texture>
					<visible>substring(listitem.filename,hdtv)</visible>
				</control>
				<control type="image" id="189">
					<include>Furniture_ListMediaFlagsVars</include>
					<texture>flags/divx.png</texture>
					<visible>substring(listitem.filename,divx)</visible>
				</control>					
			</control>			
	</include>
	
	<include name="Furniture_ShowcaseMediaFlags">
		<control type="group">
			<visible>Window.IsActive(25) + Control.IsVisible(57) + !Skin.HasSetting(nomediaflags) + Container.Content(movies) + ![Control.HasFocus(60) | Control.HasFocus(94)]</visible>
			<include>Animation_CommonFade</include>
			<control type="image">
				<posx>0</posx>
				<posy>569</posy>
				<width>298</width>
				<height>151</height>
				<texture>showcase/flagshade.png</texture>
				<include>Animation_HideShowcase</include>
				<visible>!Skin.HasSetting(darkshowcase)</visible>
			</control>
			<control type="image">
				<posx>982</posx>
				<posy>569</posy>
				<width>298</width>
				<height>151</height>
				<texture flipx="true">showcase/flagshade.png</texture>
				<include>Animation_HideShowcase</include>
				<visible>!Skin.HasSetting(darkshowcase)</visible>				
			</control>	
		</control>
		<control type="group">
			<visible>Window.IsActive(25) + Control.IsVisible(57) + !Skin.HasSetting(nomediaflags) + Container.Content(movies) + ![Control.HasFocus(60) | Control.HasFocus(94)]</visible>
			<include>Animation_CommonFade</include>
			<control type="group">
				<posx>80</posx>
				<control type="image">
					<include>Furniture_ShowcaseMediaFlagsVars</include>
					<texture>flags/default.png</texture>
					<visible>!Control.IsVisible(81) + !Skin.HasSetting(nodefaultflags)</visible>
				</control>				
					<control type="image" id="81">
					<include>Furniture_ShowcaseMediaFlagsVars</include>
					<texture>flags/Studios/007.png</texture>
					<visible>substring(listitem.studio,Bond)</visible>
				</control>
				<control type="image" id="81">
					<include>Furniture_ShowcaseMediaFlagsVars</include>
					<texture>flags/Studios/20thcenturyfox.png</texture>
					<visible>substring(listitem.studio,Fox)</visible>
				</control>	
				<control type="image" id="81">
					<include>Furniture_ShowcaseMediaFlagsVars</include>
					<texture>flags/Studios/abandon.png</texture>
					<visible>substring(listitem.studio,Abandon)</visible>
				</control>
					<control type="image" id="81">
					<include>Furniture_ShowcaseMediaFlagsVars</include>
					<texture>flags/Studios/abc.png</texture>
					<visible>substring(listitem.studio,ABC)</visible>
				</control>			
				<control type="image" id="81">
					<include>Furniture_ShowcaseMediaFlagsVars</include>
					<texture>flags/Studios/adultswim.png</texture>
					<visible>substring(listitem.studio,Swim)</visible>
				</control>					
				<control type="image" id="81">
					<include>Furniture_ShowcaseMediaFlagsVars</include>
					<texture>flags/Studios/amblin.png</texture>
					<visible>substring(listitem.studio,Amblin)</visible>
				</control>				
				<control type="image" id="81">
					<include>Furniture_ShowcaseMediaFlagsVars</include>
					<texture>flags/Studios/arte.png</texture>
					<visible>substring(listitem.studio,Arte)</visible>
				</control>					
				<control type="image" id="81">
					<include>Furniture_ShowcaseMediaFlagsVars</include>
					<texture>flags/Studios/artisan.png</texture>
					<visible>substring(listitem.studio,Artisan)</visible>
				</control>				
				<control type="image" id="81">
					<include>Furniture_ShowcaseMediaFlagsVars</include>
					<texture>flags/Studios/bbc.png</texture>
					<visible>substring(listitem.studio,BBC)</visible>
				</control>					
				<control type="image" id="81">
					<include>Furniture_ShowcaseMediaFlagsVars</include>
					<texture>flags/Studios/beacon.png</texture>
					<visible>substring(listitem.studio,Beacon)</visible>
				</control>					
				<control type="image" id="81">
					<include>Furniture_ShowcaseMediaFlagsVars</include>
					<texture>flags/Studios/buena_vista_international.png</texture>
					<visible>substring(listitem.studio,Buena)</visible>
				</control>				
				<control type="image" id="81">
					<include>Furniture_ShowcaseMediaFlagsVars</include>
					<texture>flags/Studios/studiocanal.png</texture>
					<visible>substring(listitem.studio,Studio Canal)</visible>
				</control>				
				<control type="image" id="81">
					<include>Furniture_ShowcaseMediaFlagsVars</include>
					<texture>flags/Studios/carolco.png</texture>
					<visible>substring(listitem.studio,Carolco)</visible>
				</control>				
				<control type="image" id="81">
					<include>Furniture_ShowcaseMediaFlagsVars</include>
					<texture>flags/Studios/castlerock.png</texture>
					<visible>substring(listitem.studio,Castle Rock)</visible>
				</control>				
				<control type="image" id="81">
					<include>Furniture_ShowcaseMediaFlagsVars</include>
					<texture>flags/Studios/cbs.png</texture>
					<visible>substring(listitem.studio,CBS)</visible>
				</control>							
				<control type="image" id="81">
					<include>Furniture_ShowcaseMediaFlagsVars</include>
					<texture>flags/Studios/celador.png</texture>
					<visible>substring(listitem.studio,Celador)</visible>
				</control>				
				<control type="image" id="81">
					<include>Furniture_ShowcaseMediaFlagsVars</include>
					<texture>flags/Studios/cnc.png</texture>
					<visible>substring(listitem.studio,CNC)</visible>
				</control>					
				<control type="image" id="81">
					<include>Furniture_ShowcaseMediaFlagsVars</include>
					<texture>flags/Studios/columbia.png</texture>
					<visible>substring(listitem.studio,Columbia)</visible>
				</control>	
				<control type="image" id="81">
					<include>Furniture_ShowcaseMediaFlagsVars</include>
					<texture>flags/Studios/comedycentral.png</texture>
					<visible>substring(listitem.studio,Comedy Central)</visible>
				</control>	
				<control type="image" id="81">
					<include>Furniture_ShowcaseMediaFlagsVars</include>
					<texture>flags/Studios/constantin.png</texture>
					<visible>substring(listitem.studio,Constantin)</visible>
				</control>				
				<control type="image" id="81">
					<include>Furniture_ShowcaseMediaFlagsVars</include>
					<texture>flags/Studios/czolowka.png</texture>
					<visible>substring(listitem.studio,Czolówka)</visible>
				</control>						
				<control type="image" id="81">
					<include>Furniture_ShowcaseMediaFlagsVars</include>
					<texture>flags/Studios/dc.png</texture>
					<visible>substring(listitem.studio,DC Comics)</visible>
				</control>					
				<control type="image" id="81">
					<include>Furniture_ShowcaseMediaFlagsVars</include>
					<texture>flags/Studios/dfi.png</texture>
					<visible>substring(listitem.studio,Danish Film Institute)</visible>
				</control>					
				<control type="image" id="81">
					<include>Furniture_ShowcaseMediaFlagsVars</include>
					<texture>flags/Studios/digital-playground.png</texture>
					<visible>substring(listitem.studio,Digital Playground)</visible>
				</control>					
				<control type="image" id="81">
					<include>Furniture_ShowcaseMediaFlagsVars</include>
					<texture>flags/Studios/dimension.png</texture>
					<visible>substring(listitem.studio,Dimension)</visible>
				</control>				
				<control type="image" id="81">
					<include>Furniture_ShowcaseMediaFlagsVars</include>
					<texture>flags/Studios/disney.png</texture>
					<visible>substring(listitem.studio,Disney)</visible>
				</control>
				<control type="image" id="81">
					<include>Furniture_ShowcaseMediaFlagsVars</include>
					<texture>flags/Studios/dreamworks.png</texture>
					<visible>substring(listitem.studio,DreamWorks) + !substring(listitem.genre,animation)</visible>
				</control>
				<control type="image" id="81">
					<include>Furniture_ShowcaseMediaFlagsVars</include>
					<texture>flags/Studios/dreamworks_animation.png</texture>
					<visible>substring(listitem.studio,DreamWorks) + substring(listitem.genre,animation)</visible>
				</control>			
				<control type="image" id="81">
					<include>Furniture_ShowcaseMediaFlagsVars</include>
					<texture>flags/Studios/eurimages.png</texture>
					<visible>substring(listitem.studio,EurImages)</visible>
				</control>				
				<control type="image" id="81">
					<include>Furniture_ShowcaseMediaFlagsVars</include>
					<texture>flags/Studios/europa.png</texture>
					<visible>substring(listitem.studio,Europa)</visible>
				</control>					
				<control type="image" id="81">
					<include>Furniture_ShowcaseMediaFlagsVars</include>
					<texture>flags/Studios/film_polski.png</texture>
					<visible>substring(listitem.studio,Polski)</visible>
				</control>					
				<control type="image" id="81">
					<include>Furniture_ShowcaseMediaFlagsVars</include>
					<texture>flags/Studios/channelfour.png</texture>
					<visible>substring(listitem.studio,FilmFour) | substring(listitem.studio,Channel Four)</visible>
				</control>					
				<control type="image" id="81">
					<include>Furniture_ShowcaseMediaFlagsVars</include>
					<texture>flags/Studios/focus.png</texture>
					<visible>substring(listitem.studio,Focus)</visible>
				</control>	
				<control type="image" id="81">
					<include>Furniture_ShowcaseMediaFlagsVars</include>
					<texture>flags/Studios/gaumont.png</texture>
					<visible>substring(listitem.studio,Gaumont)</visible>
				</control>				
				<control type="image" id="81">
					<include>Furniture_ShowcaseMediaFlagsVars</include>
					<texture>flags/Studios/ghibli.png</texture>
					<visible>substring(listitem.studio,Ghibli)</visible>
				</control>
				<control type="image" id="81">
					<include>Furniture_ShowcaseMediaFlagsVars</include>
					<texture>flags/Studios/gutek.png</texture>
					<visible>substring(listitem.studio,Gutek)</visible>
				</control>
				<control type="image" id="81">
					<include>Furniture_ShowcaseMediaFlagsVars</include>
					<texture>flags/Studios/happymadison.png</texture>
					<visible>substring(listitem.studio,Madison)</visible>
				</control>		
				<control type="image" id="81">
					<include>Furniture_ShowcaseMediaFlagsVars</include>
					<texture>flags/Studios/hbo.png</texture>
					<visible>substring(listitem.studio,HBO)</visible>
				</control>		
				<control type="image" id="81">
					<include>Furniture_ShowcaseMediaFlagsVars</include>
					<texture>flags/Studios/hollywood.png</texture>
					<visible>substring(listitem.studio,Hollywood)</visible>
				</control>
				<control type="image" id="81">
					<include>Furniture_ShowcaseMediaFlagsVars</include>
					<texture>flags/Studios/imagine.png</texture>
					<visible>substring(listitem.studio,Imagine)</visible>
				</control>
				<control type="image" id="81">
					<include>Furniture_ShowcaseMediaFlagsVars</include>
					<texture>flags/Studios/kadr.png</texture>
					<visible>substring(listitem.studio,Studio,Filmowe Kadr)</visible>
				</control>
				<control type="image" id="81">
					<include>Furniture_ShowcaseMediaFlagsVars</include>
					<texture>flags/Studios/kamera.png</texture>
					<visible>substring(listitem.studio,Studio,Filmowe Kamera)</visible>
				</control>
				<control type="image" id="81">
					<include>Furniture_ShowcaseMediaFlagsVars</include>
					<texture>flags/Studios/lakeshore.png</texture>
					<visible>substring(listitem.studio,Lakeshore)</visible>
				</control>	
				<control type="image" id="81">
					<include>Furniture_ShowcaseMediaFlagsVars</include>
					<texture>flags/Studios/legendary.png</texture>
					<visible>substring(listitem.studio,Legendary)</visible>
				</control>
				<control type="image" id="81">
					<include>Furniture_ShowcaseMediaFlagsVars</include>
					<texture>flags/Studios/lionsgate.png</texture>
					<visible>substring(listitem.studio,Lionsgate)</visible>
				</control>
				<control type="image" id="81">
					<include>Furniture_ShowcaseMediaFlagsVars</include>
					<texture>flags/Studios/lizard.png</texture>
					<visible>substring(listitem.studio,Lizard)</visible>
				</control>
				<control type="image" id="81">
					<include>Furniture_ShowcaseMediaFlagsVars</include>
					<texture>flags/Studios/lucasfilm.png</texture>
					<visible>substring(listitem.studio,Lucasfilm)</visible>
				</control>
				<control type="image" id="81">
					<include>Furniture_ShowcaseMediaFlagsVars</include>
					<texture>flags/Studios/magnolia.png</texture>
					<visible>substring(listitem.studio,Magnolia)</visible>
				</control>
				<control type="image" id="81">
					<include>Furniture_ShowcaseMediaFlagsVars</include>
					<texture>flags/Studios/marvel.png</texture>
					<visible>substring(listitem.studio,Marvel)</visible>
				</control>
				<control type="image" id="81">
					<include>Furniture_ShowcaseMediaFlagsVars</include>
					<texture>flags/Studios/mgm.png</texture>
					<visible>substring(listitem.studio,Mayer) | substring(listitem.studio,MGM)</visible>
				</control>
				<control type="image" id="81">
					<include>Furniture_ShowcaseMediaFlagsVars</include>
					<texture>flags/Studios/mibac.png</texture>
					<visible>substring(listitem.studio,Mibac)</visible>
				</control>				
				<control type="image" id="81">
					<include>Furniture_ShowcaseMediaFlagsVars</include>
					<texture>flags/Studios/millenium.png</texture>
					<visible>substring(listitem.studio,Millenium)</visible>
				</control>			
				<control type="image" id="81">
					<include>Furniture_ShowcaseMediaFlagsVars</include>
					<texture>flags/Studios/miramax.png</texture>
					<visible>substring(listitem.studio,Miramax)</visible>
				</control>				
				<control type="image" id="81">
					<include>Furniture_ShowcaseMediaFlagsVars</include>
					<texture>flags/Studios/monolith.png</texture>
					<visible>substring(listitem.studio,Monolith)</visible>
				</control>			
				<control type="image" id="81">
					<include>Furniture_ShowcaseMediaFlagsVars</include>
					<texture>flags/Studios/newlinecinema.png</texture>
					<visible>substring(listitem.studio,New Line)</visible>
				</control>				
				<control type="image" id="81">
					<include>Furniture_ShowcaseMediaFlagsVars</include>
					<texture>flags/Studios/newmarket.png</texture>
					<visible>substring(listitem.studio,New Market)</visible>
				</control>	
				<control type="image" id="81">
					<include>Furniture_ShowcaseMediaFlagsVars</include>
					<texture>flags/Studios/nuimage.png</texture>
					<visible>substring(listitem.studio,Nuimage)</visible>
				</control>	
				<control type="image" id="81">
					<include>Furniture_ShowcaseMediaFlagsVars</include>
					<texture>flags/Studios/orion.png</texture>
					<visible>substring(listitem.studio,Orion)</visible>
				</control>
				<control type="image" id="81">
					<include>Furniture_ShowcaseMediaFlagsVars</include>
					<texture>flags/Studios/paramount.png</texture>
					<visible>substring(listitem.studio,Paramount)</visible>
				</control>
				<control type="image" id="81">
					<include>Furniture_ShowcaseMediaFlagsVars</include>
					<texture>flags/Studios/pathe.png</texture>
					<visible>substring(listitem.studio,Pathé)</visible>
				</control>
				<control type="image" id="81">
					<include>Furniture_ShowcaseMediaFlagsVars</include>
					<texture>flags/Studios/pisf.png</texture>
					<visible>substring(listitem.studio,Filmowej)</visible>
				</control>	
				<control type="image" id="81">
					<include>Furniture_ShowcaseMediaFlagsVars</include>
					<texture>flags/Studios/pixar.png</texture>
					<visible>substring(listitem.studio,Pixar)</visible>
				</control>	 
				<control type="image" id="81">
					<include>Furniture_ShowcaseMediaFlagsVars</include>
					<texture>flags/Studios/platige.png</texture>
					<visible>substring(listitem.studio,Platige)</visible>
				</control>	 	
				<control type="image" id="81">
					<include>Furniture_ShowcaseMediaFlagsVars</include>
					<texture>flags/Studios/polsat.png</texture>
					<visible>substring(listitem.studio,Polsat)</visible>
				</control>	 	
				<control type="image" id="81">
					<include>Furniture_ShowcaseMediaFlagsVars</include>
					<texture>flags/Studios/rai.png</texture>
					<visible>substring(listitem.studio,Rai)</visible>
				</control>	 	
				<control type="image" id="81">
					<include>Furniture_ShowcaseMediaFlagsVars</include>
					<texture>flags/Studios/regency.png</texture>
					<visible>substring(listitem.studio,Regency)</visible>
				</control>		
				<control type="image" id="81">
					<include>Furniture_ShowcaseMediaFlagsVars</include>
					<texture>flags/Studios/relativity.png</texture>
					<visible>substring(listitem.studio,Relativity)</visible>
				</control>	
				<control type="image" id="81">
					<include>Furniture_ShowcaseMediaFlagsVars</include>
					<texture>flags/Studios/revolution.png</texture>
					<visible>substring(listitem.studio,Revolution)</visible>
				</control>	
				<control type="image" id="81">
					<include>Furniture_ShowcaseMediaFlagsVars</include>
					<texture>flags/Studios/scifi.png</texture>
					<visible>substring(listitem.studio,sci fi)</visible>
				</control>		
				<control type="image" id="81">
					<include>Furniture_ShowcaseMediaFlagsVars</include>
					<texture>flags/Studios/screengems.png</texture>
					<visible>substring(listitem.studio,Screen Gems)</visible>
				</control>	 
				<control type="image" id="81">
					<include>Furniture_ShowcaseMediaFlagsVars</include>
					<texture>flags/Studios/se-ma-for.png</texture>
					<visible>substring(listitem.studio,se-ma-for)</visible>
				</control>	 
				<control type="image" id="81">
					<include>Furniture_ShowcaseMediaFlagsVars</include>
					<texture>flags/Studios/sfi.png</texture>
					<visible>substring(listitem.studio,swedish film institute)</visible>
				</control>	 		
				<control type="image" id="81">
					<include>Furniture_ShowcaseMediaFlagsVars</include>
					<texture>flags/Studios/showtime.png</texture>
					<visible>substring(listitem.studio,showtime)</visible>
				</control>	 	
				<control type="image" id="81">
					<include>Furniture_ShowcaseMediaFlagsVars</include>
					<texture>flags/Studios/sonypictures.png</texture>
					<visible>substring(listitem.studio,Sony)</visible>
				</control>
				<control type="image" id="81">
					<include>Furniture_ShowcaseMediaFlagsVars</include>
					<texture>flags/Studios/syrena.png</texture>
					<visible>substring(listitem.studio,Syrena)</visible>
				</control>	
				<control type="image" id="81">
					<include>Furniture_ShowcaseMediaFlagsVars</include>
					<texture>flags/Studios/thinkfilm.png</texture>
					<visible>substring(listitem.studio,THINKFilm)</visible>
				</control>	
				<control type="image" id="81">
					<include>Furniture_ShowcaseMediaFlagsVars</include>
					<texture>flags/Studios/touchstone.png</texture>
					<visible>substring(listitem.studio,Touchstone)</visible>
				</control>
				<control type="image" id="81">
					<include>Furniture_ShowcaseMediaFlagsVars</include>
					<texture>flags/Studios/tristar.png</texture>
					<visible>substring(listitem.studio,TriStar)</visible>
				</control>
				<control type="image" id="81">
					<include>Furniture_ShowcaseMediaFlagsVars</include>
					<texture>flags/Studios/tvn.png</texture>
					<visible>substring(listitem.studio,tvn)</visible>
				</control>
				<control type="image" id="81">
					<include>Furniture_ShowcaseMediaFlagsVars</include>
					<texture>flags/Studios/tvp.png</texture>
					<visible>substring(listitem.studio,tvp)</visible>
				</control>
				<control type="image" id="81">
					<include>Furniture_ShowcaseMediaFlagsVars</include>
					<texture>flags/Studios/ugc.png</texture>
					<visible>substring(listitem.studio,ugc)</visible>
				</control>
				<control type="image" id="81">
					<include>Furniture_ShowcaseMediaFlagsVars</include>
					<texture>flags/Studios/unitedartists.png</texture>
					<visible>substring(listitem.studio,United Artists)</visible>
				</control>				
				<control type="image" id="81">
					<include>Furniture_ShowcaseMediaFlagsVars</include>
					<texture>flags/Studios/universal.png</texture>
					<visible>substring(listitem.studio,Universal)</visible>
				</control>			
				<control type="image" id="81">
					<include>Furniture_ShowcaseMediaFlagsVars</include>
					<texture>flags/Studios/village_roadshow.png</texture>
					<visible>substring(listitem.studio,Roadshow)</visible>
				</control>	
				<control type="image" id="81">
					<include>Furniture_ShowcaseMediaFlagsVars</include>
					<texture>flags/Studios/warner.png</texture>
					<visible>substring(listitem.studio,Warner)</visible>
				</control>	
				<control type="image" id="81">
					<include>Furniture_ShowcaseMediaFlagsVars</include>
					<texture>flags/Studios/wdr.png</texture>
					<visible>substring(listitem.studio,WDR)</visible>
				</control>
				<control type="image" id="81">
					<include>Furniture_ShowcaseMediaFlagsVars</include>
					<texture>flags/Studios/weinstein.png</texture>
					<visible>substring(listitem.studio,Weinstein)</visible>
				</control>	
				<control type="image" id="81">
					<include>Furniture_ShowcaseMediaFlagsVars</include>
					<texture>flags/Studios/working_title.png</texture>
					<visible>substring(listitem.studio,Working Title)</visible>
				</control>	
				<control type="image" id="81">
					<include>Furniture_ShowcaseMediaFlagsVars</include>
					<texture>flags/Studios/zebra.png</texture>
					<visible>substring(listitem.studio,Zebra)</visible>
				</control>				
				<control type="image" id="81">
					<include>Furniture_ShowcaseMediaFlagsVars</include>
					<texture>flags/Studios/zentropa.png</texture>
					<visible>substring(listitem.studio,Zentropa)</visible>
				</control>		
				<control type="image" id="81">
					<include>Furniture_ShowcaseMediaFlagsVars</include>
					<texture>flags/Studios/bad_robot.png</texture>
					<visible>substring(listitem.studio,Bad Robot)</visible>
				</control>		
				<control type="image" id="81">
					<include>Furniture_ShowcaseMediaFlagsVars</include>
					<texture>flags/Studios/thisisthat.png</texture>
					<visible>substring(listitem.studio,This Is That)</visible>
				</control>	
				<control type="image" id="81">
					<include>Furniture_ShowcaseMediaFlagsVars</include>
					<texture>flags/Studios/saul_zaentz.png</texture>
					<visible>substring(listitem.studio,Saul Zaenz)</visible>
				</control>		
				<control type="image" id="81">
					<include>Furniture_ShowcaseMediaFlagsVars</include>
					<texture>flags/Studios/pecf.png</texture>
					<visible>substring(listitem.studio,PECF)</visible>
				</control>					
				<control type="image" id="81">
					<include>Furniture_ShowcaseMediaFlagsVars</include>
					<texture>flags/Studios/scott_free.png</texture>
					<visible>substring(listitem.studio,Scott Free)</visible>
				</control>	
				<control type="image" id="81">
					<include>Furniture_ShowcaseMediaFlagsVars</include>
					<texture>flags/Studios/rhombus.png</texture>
					<visible>substring(listitem.studio,Rhombus)</visible>
				</control>	
				<control type="image" id="81">
					<include>Furniture_ShowcaseMediaFlagsVars</include>
					<texture>flags/Studios/blackdog.png</texture>
					<visible>substring(listitem.studio,Black Dog)</visible>
				</control>	
				<control type="image" id="81">
					<include>Furniture_ShowcaseMediaFlagsVars</include>
					<texture>flags/Studios/sandrew.png</texture>
					<visible>substring(listitem.studio,Sandrew)</visible>
				</control>	
				<control type="image" id="81">
					<include>Furniture_ShowcaseMediaFlagsVars</include>
					<texture>flags/Studios/jerry_bruckheimer.png</texture>
					<visible>substring(listitem.studio,Bruckheimer)</visible>
				</control>	
				<control type="image" id="81">
					<include>Furniture_ShowcaseMediaFlagsVars</include>
					<texture>flags/Studios/morgan.png</texture>
					<visible>substring(listitem.studio,Morgan)</visible>
				</control>	
				<control type="image" id="81">
					<include>Furniture_ShowcaseMediaFlagsVars</include>
					<texture>flags/Studios/rogue.png</texture>
					<visible>substring(listitem.studio,Rogue)</visible>
				</control>	
				<control type="image" id="81">
					<include>Furniture_ShowcaseMediaFlagsVars</include>
					<texture>flags/Studios/squareenix.png</texture>
					<visible>substring(listitem.studio,Enix)</visible>
				</control>
				<control type="image" id="81">
					<include>Furniture_ShowcaseMediaFlagsVars</include>
					<texture>flags/Studios/toho.png</texture>
					<visible>substring(listitem.studio,Toho)</visible>
				</control>		
			</control>
			<control type="group">
				<posx>975</posx>
				<control type="image">
					<include>Furniture_ShowcaseMediaFlagsVars</include>
					<texture>flags/defaultscreen.png</texture>
					<visible>!Control.IsVisible(83) + !Skin.HasSetting(nodefaultflags)</visible>
				</control>
			<control type="image" id="83">
					<include>Furniture_ShowcaseMediaFlagsVars</include>
					<texture>flags/sd.png</texture>
					<visible>substring(listitem.studio,sdi) | substring(listitem.studio,sdp)</visible>
				</control>
				<control type="image" id="83">
					<include>Furniture_ShowcaseMediaFlagsVars</include>
					<texture>flags/480p.png</texture>
					<visible>substring(listitem.studio,480p)</visible>
				</control>
				<control type="image" id="83">
					<include>Furniture_ShowcaseMediaFlagsVars</include>
					<texture>flags/custom/576p.png</texture>
					<visible>substring(listitem.studio,576p)</visible>
				</control>				
				<control type="image" id="83">
					<include>Furniture_ShowcaseMediaFlagsVars</include>
					<texture>flags/720p.png</texture>
					<visible>substring(listitem.studio,720p)</visible>
				</control>
				<control type="image" id="83">
					<include>Furniture_ShowcaseMediaFlagsVars</include>
					<texture>flags/1080p.png</texture>
					<visible>substring(listitem.studio,1080p)</visible>
				</control>
				<control type="image" id="83">
					<include>Furniture_ShowcaseMediaFlagsVars</include>
					<texture>flags/480i.png</texture>
					<visible>substring(listitem.studio,480i)</visible>
				</control>
				<control type="image" id="83">
					<include>Furniture_ShowcaseMediaFlagsVars</include>
					<texture>flags/576i.png</texture>
					<visible>substring(listitem.studio,576i)</visible>
				</control>				
				<control type="image" id="83">
					<include>Furniture_ShowcaseMediaFlagsVars</include>
					<texture>flags/720i.png</texture>
					<visible>substring(listitem.studio,720i)</visible>
				</control>
				<control type="image" id="83">
					<include>Furniture_ShowcaseMediaFlagsVars</include>
					<texture>flags/1080i.png</texture>
					<visible>substring(listitem.studio,1080i)</visible>
				</control>				
			</control>
			<control type="group">
				<posx>1085</posx>
				<control type="image">
					<include>Furniture_ShowcaseMediaFlagsVars</include>
					<texture>flags/defaultsound.png</texture>
					<visible>!Control.IsVisible(84) + !Skin.HasSetting(nodefaultflags)</visible>
				</control>			
				<control type="image" id="84">
					<include>Furniture_ShowcaseMediaFlagsVars</include>
					<texture>flags/custom/dtsma.png</texture>
					<visible>substring(listitem.studio,dtsma) | substring(listitem.studio,master audio) + !substring(listitem.studio,ac-3)</visible>
				</control>					
				<control type="image" id="84">
					<include>Furniture_ShowcaseMediaFlagsVars</include>
					<texture>flags/dts.png</texture>
					<visible>substring(listitem.studio,dts) + !substring(listitem.studio,ac-3) + !substring(listitem.studio,dtsma) | substring(listitem.studio,master audio)</visible>
				</control>			
				<control type="image" id="84">
					<include>Furniture_ShowcaseMediaFlagsVars</include>
					<texture>flags/custom/dolbytruehd.png</texture>
					<visible>substring(listitem.studio,truehd) | substring(listitem.studio,true hd)</visible>
				</control>	
				<control type="image" id="84">
					<include>Furniture_ShowcaseMediaFlagsVars</include>
					<texture>flags/dolbydigital.png</texture>
					<visible>substring(listitem.studio,ac-3)</visible>
				</control>
				<control type="image" id="84">
					<include>Furniture_ShowcaseMediaFlagsVars</include>
					<texture>flags/custom/mp3.png</texture>
					<visible>substring(listitem.studio,MPEG Audio)</visible>
				</control>
				<control type="image" id="84">
					<include>Furniture_ShowcaseMediaFlagsVars</include>
					<texture>flags/custom/flac.png</texture>
					<visible>substring(listitem.studio,flac)</visible>
				</control>
				<control type="image" id="84">
					<include>Furniture_ShowcaseMediaFlagsVars</include>
					<texture>flags/custom/ogg.png</texture>
					<visible>substring(listitem.studio,vorbis)</visible>
				</control>				
				<control type="image" id="84">
					<include>Furniture_ShowcaseMediaFlagsVars</include>
					<texture>flags/custom/aac.png</texture>
					<visible>substring(listitem.studio,aac)</visible>
				</control>				
			</control>
			<control type="group">
				<posx>190</posx>
				<control type="image">
					<include>Furniture_ShowcaseMediaFlagsVars</include>
					<texture>flags/defaultsource.png</texture>
					<visible>!Control.IsVisible(82) + !Skin.HasSetting(nodefaultflags)</visible>
				</control>				
					<control type="image" id="82">
					<include>Furniture_ShowcaseMediaFlagsVars</include>
					<texture>flags/hddvd.png</texture>
					<visible>substring(listitem.filename,hddvd)</visible>
				</control>
				<control type="image" id="82">
					<include>Furniture_ShowcaseMediaFlagsVars</include>
					<texture>flags/bluray.png</texture>
					<visible>substring(listitem.filename,bluray) | substring(listitem.filename,blu-ray) | substring(listitem.filename,BRRip)</visible>
				</control>
				<control type="image" id="82">
					<include>Furniture_ShowcaseMediaFlagsVars</include>
					<texture>flags/custom/dvd.png</texture>
					<visible>substring(listitem.filename,sddvd) | substring(listitem.filename,dvdrip)</visible>
				</control>
				<control type="image" id="82">
					<include>Furniture_ShowcaseMediaFlagsVars</include>
					<texture>flags/hdtv.png</texture>
					<visible>substring(listitem.filename,hdtv)</visible>
				</control>				
			</control>
		</control>
	</include>
	

	<include name="Furniture_MultiplexMediaFlags">		
		<control type="group">
			<visible>Window.IsActive(25) + Control.IsVisible(52) + !Skin.HasSetting(nomediaflags) + Container.Content(movies)</visible>
			<include>Animation_CommonFade</include>
			<include>Animation_HideMultiplex</include>			
			<control type="group">
				<posx>60</posx>
				<control type="image">
					<include>Furniture_PanelMediaFlagsVars</include>
					<texture>flags/default.png</texture>
					<visible>!Control.IsVisible(81) + !Skin.HasSetting(nodefaultflags)</visible>
				</control>				
				<control type="image" id="81">
					<include>Furniture_PanelMediaFlagsVars</include>
					<texture>flags/Studios/007.png</texture>
					<visible>substring(listitem.studio,Bond)</visible>
				</control>
				<control type="image" id="81">
					<include>Furniture_PanelMediaFlagsVars</include>
					<texture>flags/Studios/20thcenturyfox.png</texture>
					<visible>substring(listitem.studio,Fox)</visible>
				</control>	
				<control type="image" id="81">
					<include>Furniture_PanelMediaFlagsVars</include>
					<texture>flags/Studios/abandon.png</texture>
					<visible>substring(listitem.studio,Abandon)</visible>
				</control>
					<control type="image" id="81">
					<include>Furniture_PanelMediaFlagsVars</include>
					<texture>flags/Studios/abc.png</texture>
					<visible>substring(listitem.studio,ABC)</visible>
				</control>			
				<control type="image" id="81">
					<include>Furniture_PanelMediaFlagsVars</include>
					<texture>flags/Studios/adultswim.png</texture>
					<visible>substring(listitem.studio,Swim)</visible>
				</control>					
				<control type="image" id="81">
					<include>Furniture_PanelMediaFlagsVars</include>
					<texture>flags/Studios/amblin.png</texture>
					<visible>substring(listitem.studio,Amblin)</visible>
				</control>				
				<control type="image" id="81">
					<include>Furniture_PanelMediaFlagsVars</include>
					<texture>flags/Studios/arte.png</texture>
					<visible>substring(listitem.studio,Arte)</visible>
				</control>					
				<control type="image" id="81">
					<include>Furniture_PanelMediaFlagsVars</include>
					<texture>flags/Studios/artisan.png</texture>
					<visible>substring(listitem.studio,Artisan)</visible>
				</control>				
				<control type="image" id="81">
					<include>Furniture_PanelMediaFlagsVars</include>
					<texture>flags/Studios/bbc.png</texture>
					<visible>substring(listitem.studio,BBC)</visible>
				</control>					
				<control type="image" id="81">
					<include>Furniture_PanelMediaFlagsVars</include>
					<texture>flags/Studios/beacon.png</texture>
					<visible>substring(listitem.studio,Beacon)</visible>
				</control>					
				<control type="image" id="81">
					<include>Furniture_PanelMediaFlagsVars</include>
					<texture>flags/Studios/buena_vista_international.png</texture>
					<visible>substring(listitem.studio,Buena)</visible>
				</control>				
				<control type="image" id="81">
					<include>Furniture_PanelMediaFlagsVars</include>
					<texture>flags/Studios/studiocanal.png</texture>
					<visible>substring(listitem.studio,Studio Canal)</visible>
				</control>				
				<control type="image" id="81">
					<include>Furniture_PanelMediaFlagsVars</include>
					<texture>flags/Studios/carolco.png</texture>
					<visible>substring(listitem.studio,Carolco)</visible>
				</control>				
				<control type="image" id="81">
					<include>Furniture_PanelMediaFlagsVars</include>
					<texture>flags/Studios/castlerock.png</texture>
					<visible>substring(listitem.studio,Castle Rock)</visible>
				</control>				
				<control type="image" id="81">
					<include>Furniture_PanelMediaFlagsVars</include>
					<texture>flags/Studios/cbs.png</texture>
					<visible>substring(listitem.studio,CBS)</visible>
				</control>							
				<control type="image" id="81">
					<include>Furniture_PanelMediaFlagsVars</include>
					<texture>flags/Studios/celador.png</texture>
					<visible>substring(listitem.studio,Celador)</visible>
				</control>				
				<control type="image" id="81">
					<include>Furniture_PanelMediaFlagsVars</include>
					<texture>flags/Studios/cnc.png</texture>
					<visible>substring(listitem.studio,CNC)</visible>
				</control>					
				<control type="image" id="81">
					<include>Furniture_PanelMediaFlagsVars</include>
					<texture>flags/Studios/columbia.png</texture>
					<visible>substring(listitem.studio,Columbia)</visible>
				</control>	
				<control type="image" id="81">
					<include>Furniture_PanelMediaFlagsVars</include>
					<texture>flags/Studios/comedycentral.png</texture>
					<visible>substring(listitem.studio,Comedy Central)</visible>
				</control>	
				<control type="image" id="81">
					<include>Furniture_PanelMediaFlagsVars</include>
					<texture>flags/Studios/constantin.png</texture>
					<visible>substring(listitem.studio,Constantin)</visible>
				</control>				
				<control type="image" id="81">
					<include>Furniture_PanelMediaFlagsVars</include>
					<texture>flags/Studios/czolowka.png</texture>
					<visible>substring(listitem.studio,Czolówka)</visible>
				</control>						
				<control type="image" id="81">
					<include>Furniture_PanelMediaFlagsVars</include>
					<texture>flags/Studios/dc.png</texture>
					<visible>substring(listitem.studio,DC Comics)</visible>
				</control>					
				<control type="image" id="81">
					<include>Furniture_PanelMediaFlagsVars</include>
					<texture>flags/Studios/dfi.png</texture>
					<visible>substring(listitem.studio,Danish Film Institute)</visible>
				</control>					
				<control type="image" id="81">
					<include>Furniture_PanelMediaFlagsVars</include>
					<texture>flags/Studios/digital-playground.png</texture>
					<visible>substring(listitem.studio,Digital Playground)</visible>
				</control>					
				<control type="image" id="81">
					<include>Furniture_PanelMediaFlagsVars</include>
					<texture>flags/Studios/dimension.png</texture>
					<visible>substring(listitem.studio,Dimension)</visible>
				</control>				
				<control type="image" id="81">
					<include>Furniture_PanelMediaFlagsVars</include>
					<texture>flags/Studios/disney.png</texture>
					<visible>substring(listitem.studio,Disney)</visible>
				</control>			
				<control type="image" id="81">
					<include>Furniture_PanelMediaFlagsVars</include>
					<texture>flags/Studios/dreamworks.png</texture>
					<visible>substring(listitem.studio,DreamWorks)</visible>
				</control>				
				<control type="image" id="81">
					<include>Furniture_PanelMediaFlagsVars</include>
					<texture>flags/Studios/eurimages.png</texture>
					<visible>substring(listitem.studio,EurImages)</visible>
				</control>				
				<control type="image" id="81">
					<include>Furniture_PanelMediaFlagsVars</include>
					<texture>flags/Studios/europa.png</texture>
					<visible>substring(listitem.studio,Europa)</visible>
				</control>					
				<control type="image" id="81">
					<include>Furniture_PanelMediaFlagsVars</include>
					<texture>flags/Studios/film_polski.png</texture>
					<visible>substring(listitem.studio,Polski)</visible>
				</control>					
				<control type="image" id="81">
					<include>Furniture_PanelMediaFlagsVars</include>
					<texture>flags/Studios/channelfour.png</texture>
					<visible>substring(listitem.studio,FilmFour) | substring(listitem.studio,Channel Four)</visible>
				</control>					
				<control type="image" id="81">
					<include>Furniture_PanelMediaFlagsVars</include>
					<texture>flags/Studios/focus.png</texture>
					<visible>substring(listitem.studio,Focus)</visible>
				</control>	
				<control type="image" id="81">
					<include>Furniture_PanelMediaFlagsVars</include>
					<texture>flags/Studios/gaumont.png</texture>
					<visible>substring(listitem.studio,Gaumont)</visible>
				</control>				
				<control type="image" id="81">
					<include>Furniture_PanelMediaFlagsVars</include>
					<texture>flags/Studios/ghibli.png</texture>
					<visible>substring(listitem.studio,Ghibli)</visible>
				</control>
				<control type="image" id="81">
					<include>Furniture_PanelMediaFlagsVars</include>
					<texture>flags/Studios/gutek.png</texture>
					<visible>substring(listitem.studio,Gutek)</visible>
				</control>
				<control type="image" id="81">
					<include>Furniture_PanelMediaFlagsVars</include>
					<texture>flags/Studios/happymadison.png</texture>
					<visible>substring(listitem.studio,Madison)</visible>
				</control>		
				<control type="image" id="81">
					<include>Furniture_PanelMediaFlagsVars</include>
					<texture>flags/Studios/hbo.png</texture>
					<visible>substring(listitem.studio,HBO)</visible>
				</control>		
				<control type="image" id="81">
					<include>Furniture_PanelMediaFlagsVars</include>
					<texture>flags/Studios/hollywood.png</texture>
					<visible>substring(listitem.studio,Hollywood)</visible>
				</control>
				<control type="image" id="81">
					<include>Furniture_PanelMediaFlagsVars</include>
					<texture>flags/Studios/imagine.png</texture>
					<visible>substring(listitem.studio,Imagine)</visible>
				</control>
				<control type="image" id="81">
					<include>Furniture_PanelMediaFlagsVars</include>
					<texture>flags/Studios/kadr.png</texture>
					<visible>substring(listitem.studio,Studio,Filmowe Kadr)</visible>
				</control>
				<control type="image" id="81">
					<include>Furniture_PanelMediaFlagsVars</include>
					<texture>flags/Studios/kamera.png</texture>
					<visible>substring(listitem.studio,Studio,Filmowe Kamera)</visible>
				</control>
				<control type="image" id="81">
					<include>Furniture_PanelMediaFlagsVars</include>
					<texture>flags/Studios/lakeshore.png</texture>
					<visible>substring(listitem.studio,Lakeshore)</visible>
				</control>	
				<control type="image" id="81">
					<include>Furniture_PanelMediaFlagsVars</include>
					<texture>flags/Studios/legendary.png</texture>
					<visible>substring(listitem.studio,Legendary)</visible>
				</control>
				<control type="image" id="81">
					<include>Furniture_PanelMediaFlagsVars</include>
					<texture>flags/Studios/lionsgate.png</texture>
					<visible>substring(listitem.studio,Lionsgate)</visible>
				</control>
				<control type="image" id="81">
					<include>Furniture_PanelMediaFlagsVars</include>
					<texture>flags/Studios/lizard.png</texture>
					<visible>substring(listitem.studio,Lizard)</visible>
				</control>
				<control type="image" id="81">
					<include>Furniture_PanelMediaFlagsVars</include>
					<texture>flags/Studios/lucasfilm.png</texture>
					<visible>substring(listitem.studio,Lucasfilm)</visible>
				</control>
				<control type="image" id="81">
					<include>Furniture_PanelMediaFlagsVars</include>
					<texture>flags/Studios/magnolia.png</texture>
					<visible>substring(listitem.studio,Magnolia)</visible>
				</control>
				<control type="image" id="81">
					<include>Furniture_PanelMediaFlagsVars</include>
					<texture>flags/Studios/marvel.png</texture>
					<visible>substring(listitem.studio,Marvel)</visible>
				</control>
				<control type="image" id="81">
					<include>Furniture_PanelMediaFlagsVars</include>
					<texture>flags/Studios/mgm.png</texture>
					<visible>substring(listitem.studio,Mayer) | substring(listitem.studio,MGM)</visible>
				</control>
				<control type="image" id="81">
					<include>Furniture_PanelMediaFlagsVars</include>
					<texture>flags/Studios/mibac.png</texture>
					<visible>substring(listitem.studio,Mibac)</visible>
				</control>				
				<control type="image" id="81">
					<include>Furniture_PanelMediaFlagsVars</include>
					<texture>flags/Studios/millenium.png</texture>
					<visible>substring(listitem.studio,Millenium)</visible>
				</control>			
				<control type="image" id="81">
					<include>Furniture_PanelMediaFlagsVars</include>
					<texture>flags/Studios/miramax.png</texture>
					<visible>substring(listitem.studio,Miramax)</visible>
				</control>				
				<control type="image" id="81">
					<include>Furniture_PanelMediaFlagsVars</include>
					<texture>flags/Studios/monolith.png</texture>
					<visible>substring(listitem.studio,Monolith)</visible>
				</control>			
				<control type="image" id="81">
					<include>Furniture_PanelMediaFlagsVars</include>
					<texture>flags/Studios/newlinecinema.png</texture>
					<visible>substring(listitem.studio,New Line)</visible>
				</control>				
				<control type="image" id="81">
					<include>Furniture_PanelMediaFlagsVars</include>
					<texture>flags/Studios/newmarket.png</texture>
					<visible>substring(listitem.studio,New Market)</visible>
				</control>	
				<control type="image" id="81">
					<include>Furniture_PanelMediaFlagsVars</include>
					<texture>flags/Studios/nuimage.png</texture>
					<visible>substring(listitem.studio,Nuimage)</visible>
				</control>	
				<control type="image" id="81">
					<include>Furniture_PanelMediaFlagsVars</include>
					<texture>flags/Studios/orion.png</texture>
					<visible>substring(listitem.studio,Orion)</visible>
				</control>
				<control type="image" id="81">
					<include>Furniture_PanelMediaFlagsVars</include>
					<texture>flags/Studios/paramount.png</texture>
					<visible>substring(listitem.studio,Paramount)</visible>
				</control>
				<control type="image" id="81">
					<include>Furniture_PanelMediaFlagsVars</include>
					<texture>flags/Studios/pathe.png</texture>
					<visible>substring(listitem.studio,Pathé)</visible>
				</control>
				<control type="image" id="81">
					<include>Furniture_PanelMediaFlagsVars</include>
					<texture>flags/Studios/pisf.png</texture>
					<visible>substring(listitem.studio,Filmowej)</visible>
				</control>	
				<control type="image" id="81">
					<include>Furniture_PanelMediaFlagsVars</include>
					<texture>flags/Studios/pixar.png</texture>
					<visible>substring(listitem.studio,Pixar)</visible>
				</control>	 
				<control type="image" id="81">
					<include>Furniture_PanelMediaFlagsVars</include>
					<texture>flags/Studios/platige.png</texture>
					<visible>substring(listitem.studio,Platige)</visible>
				</control>	 	
				<control type="image" id="81">
					<include>Furniture_PanelMediaFlagsVars</include>
					<texture>flags/Studios/polsat.png</texture>
					<visible>substring(listitem.studio,Polsat)</visible>
				</control>	 	
				<control type="image" id="81">
					<include>Furniture_PanelMediaFlagsVars</include>
					<texture>flags/Studios/rai.png</texture>
					<visible>substring(listitem.studio,Rai)</visible>
				</control>	 	
				<control type="image" id="81">
					<include>Furniture_PanelMediaFlagsVars</include>
					<texture>flags/Studios/regency.png</texture>
					<visible>substring(listitem.studio,Regency)</visible>
				</control>		
				<control type="image" id="81">
					<include>Furniture_PanelMediaFlagsVars</include>
					<texture>flags/Studios/relativity.png</texture>
					<visible>substring(listitem.studio,Relativity)</visible>
				</control>	
				<control type="image" id="81">
					<include>Furniture_PanelMediaFlagsVars</include>
					<texture>flags/Studios/revolution.png</texture>
					<visible>substring(listitem.studio,Revolution)</visible>
				</control>	
				<control type="image" id="81">
					<include>Furniture_PanelMediaFlagsVars</include>
					<texture>flags/Studios/scifi.png</texture>
					<visible>substring(listitem.studio,sci fi)</visible>
				</control>		
				<control type="image" id="81">
					<include>Furniture_PanelMediaFlagsVars</include>
					<texture>flags/Studios/screengems.png</texture>
					<visible>substring(listitem.studio,Screen Gems)</visible>
				</control>	 
				<control type="image" id="81">
					<include>Furniture_PanelMediaFlagsVars</include>
					<texture>flags/Studios/se-ma-for.png</texture>
					<visible>substring(listitem.studio,se-ma-for)</visible>
				</control>	 
				<control type="image" id="81">
					<include>Furniture_PanelMediaFlagsVars</include>
					<texture>flags/Studios/sfi.png</texture>
					<visible>substring(listitem.studio,swedish film institute)</visible>
				</control>	 		
				<control type="image" id="81">
					<include>Furniture_PanelMediaFlagsVars</include>
					<texture>flags/Studios/showtime.png</texture>
					<visible>substring(listitem.studio,showtime)</visible>
				</control>	 	
				<control type="image" id="81">
					<include>Furniture_PanelMediaFlagsVars</include>
					<texture>flags/Studios/sonypictures.png</texture>
					<visible>substring(listitem.studio,Sony)</visible>
				</control>
				<control type="image" id="81">
					<include>Furniture_PanelMediaFlagsVars</include>
					<texture>flags/Studios/syrena.png</texture>
					<visible>substring(listitem.studio,Syrena)</visible>
				</control>	
				<control type="image" id="81">
					<include>Furniture_PanelMediaFlagsVars</include>
					<texture>flags/Studios/thinkfilm.png</texture>
					<visible>substring(listitem.studio,THINKFilm)</visible>
				</control>	
				<control type="image" id="81">
					<include>Furniture_PanelMediaFlagsVars</include>
					<texture>flags/Studios/touchstone.png</texture>
					<visible>substring(listitem.studio,Touchstone)</visible>
				</control>
				<control type="image" id="81">
					<include>Furniture_PanelMediaFlagsVars</include>
					<texture>flags/Studios/tristar.png</texture>
					<visible>substring(listitem.studio,TriStar)</visible>
				</control>
				<control type="image" id="81">
					<include>Furniture_PanelMediaFlagsVars</include>
					<texture>flags/Studios/tvn.png</texture>
					<visible>substring(listitem.studio,tvn)</visible>
				</control>
				<control type="image" id="81">
					<include>Furniture_PanelMediaFlagsVars</include>
					<texture>flags/Studios/tvp.png</texture>
					<visible>substring(listitem.studio,tvp)</visible>
				</control>
				<control type="image" id="81">
					<include>Furniture_PanelMediaFlagsVars</include>
					<texture>flags/Studios/ugc.png</texture>
					<visible>substring(listitem.studio,ugc)</visible>
				</control>
				<control type="image" id="81">
					<include>Furniture_PanelMediaFlagsVars</include>
					<texture>flags/Studios/unitedartists.png</texture>
					<visible>substring(listitem.studio,United Artists)</visible>
				</control>				
				<control type="image" id="81">
					<include>Furniture_PanelMediaFlagsVars</include>
					<texture>flags/Studios/universal.png</texture>
					<visible>substring(listitem.studio,Universal)</visible>
				</control>			
				<control type="image" id="81">
					<include>Furniture_PanelMediaFlagsVars</include>
					<texture>flags/Studios/village_roadshow.png</texture>
					<visible>substring(listitem.studio,Roadshow)</visible>
				</control>	
				<control type="image" id="81">
					<include>Furniture_PanelMediaFlagsVars</include>
					<texture>flags/Studios/warner.png</texture>
					<visible>substring(listitem.studio,Warner)</visible>
				</control>	
				<control type="image" id="81">
					<include>Furniture_PanelMediaFlagsVars</include>
					<texture>flags/Studios/wdr.png</texture>
					<visible>substring(listitem.studio,WDR)</visible>
				</control>
				<control type="image" id="81">
					<include>Furniture_PanelMediaFlagsVars</include>
					<texture>flags/Studios/weinstein.png</texture>
					<visible>substring(listitem.studio,Weinstein)</visible>
				</control>	
				<control type="image" id="81">
					<include>Furniture_PanelMediaFlagsVars</include>
					<texture>flags/Studios/working_title.png</texture>
					<visible>substring(listitem.studio,Working Title)</visible>
				</control>	
				<control type="image" id="81">
					<include>Furniture_PanelMediaFlagsVars</include>
					<texture>flags/Studios/zebra.png</texture>
					<visible>substring(listitem.studio,Zebra)</visible>
				</control>				
				<control type="image" id="81">
					<include>Furniture_PanelMediaFlagsVars</include>
					<texture>flags/Studios/zentropa.png</texture>
					<visible>substring(listitem.studio,Zentropa)</visible>
				</control>		
				<control type="image" id="81">
					<include>Furniture_PanelMediaFlagsVars</include>
					<texture>flags/Studios/bad_robot.png</texture>
					<visible>substring(listitem.studio,Bad Robot)</visible>
				</control>		
				<control type="image" id="81">
					<include>Furniture_PanelMediaFlagsVars</include>
					<texture>flags/Studios/thisisthat.png</texture>
					<visible>substring(listitem.studio,This Is That)</visible>
				</control>	
				<control type="image" id="81">
					<include>Furniture_PanelMediaFlagsVars</include>
					<texture>flags/Studios/saul_zaentz.png</texture>
					<visible>substring(listitem.studio,Saul Zaenz)</visible>
				</control>		
				<control type="image" id="81">
					<include>Furniture_PanelMediaFlagsVars</include>
					<texture>flags/Studios/pecf.png</texture>
					<visible>substring(listitem.studio,PECF)</visible>
				</control>					
				<control type="image" id="81">
					<include>Furniture_PanelMediaFlagsVars</include>
					<texture>flags/Studios/scott_free.png</texture>
					<visible>substring(listitem.studio,Scott Free)</visible>
				</control>	
				<control type="image" id="81">
					<include>Furniture_PanelMediaFlagsVars</include>
					<texture>flags/Studios/rhombus.png</texture>
					<visible>substring(listitem.studio,Rhombus)</visible>
				</control>	
				<control type="image" id="81">
					<include>Furniture_PanelMediaFlagsVars</include>
					<texture>flags/Studios/blackdog.png</texture>
					<visible>substring(listitem.studio,Black Dog)</visible>
				</control>	
				<control type="image" id="81">
					<include>Furniture_PanelMediaFlagsVars</include>
					<texture>flags/Studios/sandrew.png</texture>
					<visible>substring(listitem.studio,Sandrew)</visible>
				</control>	
				<control type="image" id="81">
					<include>Furniture_PanelMediaFlagsVars</include>
					<texture>flags/Studios/jerry_bruckheimer.png</texture>
					<visible>substring(listitem.studio,Bruckheimer)</visible>
				</control>	
				<control type="image" id="81">
					<include>Furniture_PanelMediaFlagsVars</include>
					<texture>flags/Studios/morgan.png</texture>
					<visible>substring(listitem.studio,Morgan)</visible>
				</control>	
				<control type="image" id="81">
					<include>Furniture_PanelMediaFlagsVars</include>
					<texture>flags/Studios/rogue.png</texture>
					<visible>substring(listitem.studio,Rogue)</visible>
				</control>	
				<control type="image" id="81">
					<include>Furniture_PanelMediaFlagsVars</include>
					<texture>flags/Studios/squareenix.png</texture>
					<visible>substring(listitem.studio,Enix)</visible>
				</control>
				<control type="image" id="81">
					<include>Furniture_PanelMediaFlagsVars</include>
					<texture>flags/Studios/toho.png</texture>
					<visible>substring(listitem.studio,Toho)</visible>
				</control>	
			</control>
			<control type="group">
				<posx>1005</posx>
				<control type="image">
					<include>Furniture_PanelMediaFlagsVars</include>
					<texture>flags/defaultscreen.png</texture>
					<visible>!Control.IsVisible(83) + !Skin.HasSetting(nodefaultflags)</visible>
				</control>
				<control type="image" id="83">
					<include>Furniture_PanelMediaFlagsVars</include>
					<texture>flags/sd.png</texture>
					<visible>substring(listitem.studio,sd)</visible>
				</control>
				<control type="image" id="83">
					<include>Furniture_PanelMediaFlagsVars</include>
					<texture>flags/480p.png</texture>
					<visible>substring(listitem.studio,480p)</visible>
				</control>
				<control type="image" id="83">
					<include>Furniture_PanelMediaFlagsVars</include>
					<texture>flags/custom/576p.png</texture>
					<visible>substring(listitem.studio,576p)</visible>
				</control>				
				<control type="image" id="83">
					<include>Furniture_PanelMediaFlagsVars</include>
					<texture>flags/720p.png</texture>
					<visible>substring(listitem.studio,720p)</visible>
				</control>
				<control type="image" id="83">
					<include>Furniture_PanelMediaFlagsVars</include>
					<texture>flags/1080p.png</texture>
					<visible>substring(listitem.studio,1080p)</visible>
				</control>
				<control type="image" id="83">
					<include>Furniture_PanelMediaFlagsVars</include>
					<texture>flags/480i.png</texture>
					<visible>substring(listitem.studio,480i)</visible>
				</control>
				<control type="image" id="83">
					<include>Furniture_PanelMediaFlagsVars</include>
					<texture>flags/576i.png</texture>
					<visible>substring(listitem.studio,576i)</visible>
				</control>				
				<control type="image" id="83">
					<include>Furniture_PanelMediaFlagsVars</include>
					<texture>flags/720i.png</texture>
					<visible>substring(listitem.studio,720i)</visible>
				</control>
				<control type="image" id="83">
					<include>Furniture_PanelMediaFlagsVars</include>
					<texture>flags/1080i.png</texture>
					<visible>substring(listitem.studio,1080i)</visible>
				</control>				
			</control>
			<control type="group">
				<posx>1115</posx>
				<control type="image">
					<include>Furniture_PanelMediaFlagsVars</include>
					<texture>flags/defaultsound.png</texture>
					<visible>!Control.IsVisible(84) + !Skin.HasSetting(nodefaultflags)</visible>
				</control>					
				<control type="image" id="84">
					<include>Furniture_PanelMediaFlagsVars</include>
					<texture>flags/custom/dtsma.png</texture>
					<visible>substring(listitem.studio,dtsma) | substring(listitem.studio,master audio) + !substring(listitem.studio,ac-3)</visible>
				</control>					
				<control type="image" id="84">
					<include>Furniture_PanelMediaFlagsVars</include>
					<texture>flags/dts.png</texture>
					<visible>substring(listitem.studio,dts) + !substring(listitem.studio,ac-3) + !substring(listitem.studio,dtsma) | substring(listitem.studio,master audio)</visible>
				</control>			
				<control type="image" id="84">
					<include>Furniture_PanelMediaFlagsVars</include>
					<texture>flags/custom/dolbyruehd.png</texture>
					<visible>substring(listitem.studio,truehd) | substring(listitem.studio,true hd)</visible>
				</control>	
				<control type="image" id="84">
					<include>Furniture_PanelMediaFlagsVars</include>
					<texture>flags/dolbydigital.png</texture>
					<visible>substring(listitem.studio,ac-3)</visible>
				</control>
				<control type="image" id="84">
					<include>Furniture_PanelMediaFlagsVars</include>
					<texture>flags/custom/mp3.png</texture>
					<visible>substring(listitem.studio,MPEG Audio)</visible>
				</control>
				<control type="image" id="84">
					<include>Furniture_PanelMediaFlagsVars</include>
					<texture>flags/custom/flac.png</texture>
					<visible>substring(listitem.studio,flac)</visible>
				</control>
				<control type="image" id="84">
					<include>Furniture_PanelMediaFlagsVars</include>
					<texture>flags/custom/ogg.png</texture>
					<visible>substring(listitem.studio,vorbis)</visible>
				</control>				
				<control type="image" id="84">
					<include>Furniture_PanelMediaFlagsVars</include>
					<texture>flags/custom/aac.png</texture>
					<visible>substring(listitem.studio,aac)</visible>
				</control>	
			</control>
			<control type="group">
				<posx>170</posx>
				<control type="image">
					<include>Furniture_PanelMediaFlagsVars</include>
					<texture>flags/defaultsource.png</texture>
					<visible>!Control.IsVisible(82) + !Skin.HasSetting(nodefaultflags)</visible>
				</control>				
					<control type="image" id="82">
					<include>Furniture_PanelMediaFlagsVars</include>
					<texture>flags/hddvd.png</texture>
					<visible>substring(listitem.filename,hddvd)</visible>
				</control>
				<control type="image" id="82">
					<include>Furniture_PanelMediaFlagsVars</include>
					<texture>flags/bluray.png</texture>
					<visible>substring(listitem.filename,bluray) | substring(listitem.filename,blu-ray) | substring(listitem.filename,BRRip)</visible>
				</control>
				<control type="image" id="82">
					<include>Furniture_PanelMediaFlagsVars</include>
					<texture>flags/custom/dvd.png</texture>
					<visible>substring(listitem.filename,sddvd) | substring(listitem.filename,dvdrip)</visible>
				</control>
				<control type="image" id="82">
					<include>Furniture_PanelMediaFlagsVars</include>
					<texture>flags/hdtv.png</texture>
					<visible>substring(listitem.filename,hdtv)</visible>
				</control>			
			</control>
		</control>		
	</include>
	
  <include name="Furniture_EpisodeMediaFlags">
        <posy>94</posy>
        <width>74</width>
        <height>50</height>
        <colordiffuse>94FFFFFF</colordiffuse>
        <control type="group">
			<visible>Window.IsActive(25) + Control.IsVisible(52) + !Skin.HasSetting(nomediaflags) + Container.Content(episodes)</visible>
			<include>Animation_CommonFade</include>
			<include>Animation_HideMultiplex</include>			
            <control type="group">
                <posx>339</posx>
                <control type="image">
                    <include>Furniture_EpisodeMediaFlags</include>
                    <texture>flags/tv/default.png</texture>
                    <visible>!Control.IsVisible(81) + !Skin.HasSetting(nodefaultflags)</visible>
                </control>
				<control type="image" id="81">
					<include>Furniture_EpisodeMediaFlags</include>
					<texture>flags/tv/a&e.png</texture>
					<visible>substring(listitem.director,netA&E)</visible>
				</control>
				<control type="image" id="81">
					<include>Furniture_EpisodeMediaFlags</include>
					<texture>flags/tv/abc.png</texture>
					<visible>substring(listitem.director,netabc) + !substring(listitem.director,1080) + !substring(listitem.director,720)</visible>
				</control>
				<control type="image" id="81">
					<include>Furniture_EpisodeMediaFlags</include>
					<texture>flags/tv/abc_hd.png</texture>
					<visible>substring(listitem.director,netabc)</visible>
					<visible>substring(listitem.director,1080) | substring(listitem.director,720)</visible>
				</control>
				<control type="image" id="81">
					<include>Furniture_EpisodeMediaFlags</include>
					<texture>flags/tv/bbc.png</texture>
					<visible>substring(listitem.director,netbbc) + !substring(listitem.director,netbbc-1) + !substring(listitem.director,netbbc-3)</visible>
				</control>
				<control type="image" id="81">
					<include>Furniture_EpisodeMediaFlags</include>
					<texture>flags/tv/bbc_one.png</texture>
					<visible>substring(listitem.director,netbbc-1) + !substring(listitem.director,1080) + !substring(listitem.director,720)</visible>
				</control>
				<control type="image" id="81">
					<include>Furniture_EpisodeMediaFlags</include>
					<texture>flags/tv/bbc_three.png</texture>
					<visible>substring(listitem.director,netbbc-3) + !substring(listitem.director,1080) + !substring(listitem.director,720)</visible>
				</control>
				<control type="image" id="81">
					<include>Furniture_EpisodeMediaFlags</include>
					<texture>flags/tv/bbc_hd.png</texture>
					<visible>substring(listitem.director,netbbc)</visible>
					<visible>substring(listitem.director,1080) | substring(listitem.director,720)</visible>
				</control>
				<control type="image" id="81">
					<include>Furniture_EpisodeMediaFlags</include>
					<texture>flags/tv/cbs.png</texture>
					<visible>substring(listitem.director,netCBS) + !substring(listitem.director,1080) + !substring(listitem.director,720)</visible>
				</control>
				<control type="image" id="81">
					<include>Furniture_EpisodeMediaFlags</include>
					<texture>flags/tv/cbs_hd.png</texture>
					<visible>substring(listitem.director,netCBS)</visible>
					<visible>substring(listitem.director,1080) | substring(listitem.director,720)</visible>
				</control>
				<control type="image" id="81">
					<include>Furniture_EpisodeMediaFlags</include>
					<texture>flags/tv/lifetime.png</texture>
					<visible>substring(listitem.director,netLifetime) + !substring(listitem.director,1080) + !substring(listitem.director,720)</visible>
				</control>
				<control type="image" id="81">
					<include>Furniture_EpisodeMediaFlags</include>
					<texture>flags/tv/lifetime_hd.png</texture>
					<visible>substring(listitem.director,netLifetime)</visible>
					<visible>substring(listitem.director,1080) | substring(listitem.director,720)</visible>
				</control>
				<control type="image" id="81">
					<include>Furniture_EpisodeMediaFlags</include>
					<texture>flags/tv/comedycentral.png</texture>
					<visible>substring(listitem.director,netComedy Central)</visible>
				</control>
				<control type="image" id="81">
					<include>Furniture_EpisodeMediaFlags</include>
					<texture>flags/tv/adultswim.png</texture>
					<visible>substring(listitem.director,Adult Swim)</visible>
				</control>
				<control type="image" id="81">
					<include>Furniture_EpisodeMediaFlags</include>
					<texture>flags/tv/hbo.png</texture>
					<visible>substring(listitem.director,netHBO) + !substring(listitem.director,1080) + !substring(listitem.director,720)</visible>
				</control>
				<control type="image" id="81">
					<include>Furniture_EpisodeMediaFlags</include>
					<texture>flags/tv/hbo_hd.png</texture>
					<visible>substring(listitem.director,netHBO)</visible>
					<visible>substring(listitem.director,1080) | substring(listitem.director,720)</visible>
				</control>
				<control type="image" id="81">
					<include>Furniture_EpisodeMediaFlags</include>
					<texture>flags/tv/foodnetwork.png</texture>
					<visible>substring(listitem.director,netFood Network)</visible>
				</control>
				<control type="image" id="81">
					<include>Furniture_EpisodeMediaFlags</include>
					<texture>flags/tv/spike.png</texture>
					<visible>substring(listitem.director,netSpike)</visible>
				</control>
				<control type="image" id="81">
					<include>Furniture_EpisodeMediaFlags</include>
					<texture>flags/tv/cartoon.png</texture>
					<visible>substring(listitem.director,netCartoon Network) + !substring(listitem.director,1080) + !substring(listitem.director,720)</visible>
				</control>
				<control type="image" id="81">
					<include>Furniture_EpisodeMediaFlags</include>
					<texture>flags/tv/cartoon_network_hd.png</texture>
					<visible>substring(listitem.director,netCartoon Network)</visible>
					<visible>substring(listitem.director,1080) | substring(listitem.director,720)</visible>
				</control>
				<control type="image" id="81">
					<include>Furniture_EpisodeMediaFlags</include>
					<texture>flags/tv/mtv.png</texture>
					<visible>substring(listitem.director,netMTV)</visible>
				</control>
				<control type="image" id="81">
					<include>Furniture_EpisodeMediaFlags</include>
					<texture>flags/tv/fox.png</texture>
					<visible>substring(listitem.director,netFox) + !substring(listitem.director,1080) + !substring(listitem.director,720)</visible>
				</control>
				<control type="image" id="81">
					<include>Furniture_EpisodeMediaFlags</include>
					<texture>flags/tv/fox_hd.png</texture>
					<visible>substring(listitem.director,netFox)</visible>
					<visible>substring(listitem.director,1080) | substring(listitem.director,720)</visible>
				</control>
				<control type="image" id="81">
					<include>Furniture_EpisodeMediaFlags</include>
					<texture>flags/tv/nbc.png</texture>
					<visible>substring(listitem.director,netnbc)</visible>
				</control>
				<control type="image" id="81">
					<include>Furniture_EpisodeMediaFlags</include>
					<texture>flags/tv/nbc.png</texture>
					<visible>substring(listitem.director,netnbc) + !substring(listitem.director,1080) + !substring(listitem.director,720)</visible>
				</control>
				<control type="image" id="81">
					<include>Furniture_EpisodeMediaFlags</include>
					<texture>flags/tv/nbc_hd.png</texture>
					<visible>substring(listitem.director,netnbc)</visible>
					<visible>substring(listitem.director,1080) | substring(listitem.director,720)</visible>
				</control>
				<control type="image" id="81">
					<include>Furniture_EpisodeMediaFlags</include>
					<texture>flags/tv/scifi.png</texture>
					<visible>substring(listitem.director,SciFi) + !substring(listitem.director,1080) + !substring(listitem.director,720)</visible>
				</control>
				<control type="image" id="81">
					<include>Furniture_EpisodeMediaFlags</include>
					<texture>flags/tv/scifihd.png</texture>
					<visible>substring(listitem.director,SciFi)</visible>
					<visible>substring(listitem.director,1080) | substring(listitem.director,720)</visible>
				</control>
				<control type="image" id="81">
					<include>Furniture_EpisodeMediaFlags</include>
					<texture>flags/tv/usa.png</texture>
					<visible>substring(listitem.director,netUSA)</visible>
				</control>
				<control type="image" id="81">
					<include>Furniture_EpisodeMediaFlags</include>
					<texture>flags/tv/syndicated.png</texture>
					<visible>substring(listitem.director,netSyndicated)</visible>
				</control>
		
				<control type="image" id="81">
					<include>Furniture_EpisodeMediaFlags</include>
					<texture>flags/tv/amc.png</texture>
					<visible>substring(listitem.director,netAMC)</visible>
				</control>				
				<control type="image" id="81">
					<include>Furniture_EpisodeMediaFlags</include>
					<texture>flags/tv/animalplanet.png</texture>
					<visible>substring(listitem.director,netAnimal Planet)</visible>
				</control>				
				<control type="image" id="81">
					<include>Furniture_EpisodeMediaFlags</include>
					<texture>flags/tv/bet.png</texture>
					<visible>substring(listitem.director,netBET)</visible>
				</control>				
				<control type="image" id="81">
					<include>Furniture_EpisodeMediaFlags</include>
					<texture>flags/tv/bravo.png</texture>
					<visible>substring(listitem.director,netBravo)</visible>
				</control>				
				<control type="image" id="81">
					<include>Furniture_EpisodeMediaFlags</include>
					<texture>flags/tv/channel4uk.png</texture>
					<visible>substring(listitem.director,netChannel 4)</visible>
				</control>				
				<control type="image" id="81">
					<include>Furniture_EpisodeMediaFlags</include>
					<texture>flags/tv/discovery.png</texture>
					<visible>substring(listitem.director,netDiscovery)</visible>
				</control>				
				<control type="image" id="81">
					<include>Furniture_EpisodeMediaFlags</include>
					<texture>flags/tv/disney.png</texture>
					<visible>substring(listitem.director,netDisney)</visible>
				</control>				
				<control type="image" id="81">
					<include>Furniture_EpisodeMediaFlags</include>
					<texture>flags/tv/espn.png</texture>
					<visible>substring(listitem.director,netESPN)</visible>
				</control>				
				<control type="image" id="81">
					<include>Furniture_EpisodeMediaFlags</include>
					<texture>flags/tv/fx.png</texture>
					<visible>substring(listitem.director,netFX)</visible>
				</control>				
				<control type="image" id="81">
					<include>Furniture_EpisodeMediaFlags</include>
					<texture>flags/tv/history.png</texture>
					<visible>substring(listitem.director,netHistory)</visible>
				</control>				
				<control type="image" id="81">
					<include>Furniture_EpisodeMediaFlags</include>
					<texture>flags/tv/mtv.png</texture>
					<visible>substring(listitem.director,netMTV)</visible>
				</control>				
				<control type="image" id="81">
					<include>Furniture_EpisodeMediaFlags</include>
					<texture>flags/tv/nickelodeon.png</texture>
					<visible>substring(listitem.director,netNickelodeon)</visible>
				</control>				
				<control type="image" id="81">
					<include>Furniture_EpisodeMediaFlags</include>
					<texture>flags/tv/showtime.png</texture>
					<visible>substring(listitem.director,netShowtime)</visible>
				</control>
				<control type="image" id="81">
					<include>Furniture_EpisodeMediaFlags</include>
					<texture>flags/tv/showtime.png</texture>
					<visible>substring(listitem.director,netshowtime) + !substring(listitem.director,1080) + !substring(listitem.director,720)</visible>
				</control>
				<control type="image" id="81">
					<include>Furniture_EpisodeMediaFlags</include>
					<texture>flags/tv/showtime_hd.png</texture>
					<visible>substring(listitem.director,netshowtime)</visible>
					<visible>substring(listitem.director,1080) | substring(listitem.director,720)</visible>
				</control>			
				<control type="image" id="81">
					<include>Furniture_EpisodeMediaFlags</include>
					<texture>flags/tv/spike.png</texture>
					<visible>substring(listitem.director,netSpike)</visible>
				</control>				
				<control type="image" id="81">
					<include>Furniture_EpisodeMediaFlags</include>
					<texture>flags/tv/tbs.png</texture>
					<visible>substring(listitem.director,netTBS)</visible>
				</control>				
				<control type="image" id="81">
					<include>Furniture_EpisodeMediaFlags</include>
					<texture>flags/tv/tnt.png</texture>
					<visible>substring(listitem.director,netTNT)</visible>
				</control>				
				<control type="image" id="81">
					<include>Furniture_EpisodeMediaFlags</include>
					<texture>flags/tv/upn.png</texture>
					<visible>substring(listitem.director,netUPN)</visible>
				</control>				
				<control type="image" id="81">
					<include>Furniture_EpisodeMediaFlags</include>
					<texture>flags/tv/versus.png</texture>
					<visible>substring(listitem.director,netVersus)</visible>
				</control>				
				<control type="image" id="81">
					<include>Furniture_EpisodeMediaFlags</include>
					<texture>flags/tv/vh1.png</texture>
					<visible>substring(listitem.director,netVH1)</visible>
				</control>				
				<control type="image" id="81">
					<include>Furniture_EpisodeMediaFlags</include>
					<texture>flags/tv/wgn.png</texture>
					<visible>substring(listitem.director,netWGN)</visible>
				</control>
<!-- For specific shows -->
				<control type="image" id="81">
					<include>Furniture_EpisodeMediaFlags</include>
					<texture>flags/tv/babylonian.png</texture>
					<visible>substring(listitem.director,netSyndicated) + substring(listitem.TVShowTitle,Babylon)</visible>
				</control>  				
<!-- For specific shows -->
				</control>

			<control type="group">
				<posx>418</posx>
				<control type="image">
					<include>Furniture_EpisodeMediaFlags</include>
					<texture>flags/defaultsource.png</texture>
					<visible>!Control.IsVisible(82) + !Skin.HasSetting(nodefaultflags)</visible>
				</control>				
				<control type="image">
					<include>Furniture_EpisodeMediaFlags</include>
					<texture>flags/defaultsource.png</texture>
					<visible>!Control.IsVisible(82) + !Skin.HasSetting(nodefaultflags)</visible>
				</control>				
					<control type="image" id="82">
					<include>Furniture_EpisodeMediaFlags</include>
					<texture>flags/hddvd.png</texture>
					<visible>substring(listitem.filename,hddvd)</visible>
				</control>
				<control type="image" id="82">
					<include>Furniture_EpisodeMediaFlags</include>
					<texture>flags/bluray.png</texture>
					<visible>substring(listitem.filename,bluray) | substring(listitem.filename,blu-ray) | substring(listitem.filename,BRRip)</visible>
				</control>
				<control type="image" id="82">
					<include>Furniture_EpisodeMediaFlags</include>
					<texture>flags/custom/dvd.png</texture>
					<visible>substring(listitem.filename,sddvd) | substring(listitem.filename,dvdrip)</visible>
				</control>
				<control type="image" id="82">
					<include>Furniture_EpisodeMediaFlags</include>
					<texture>flags/hdtv.png</texture>
					<visible>substring(listitem.filename,hdtv)</visible>
				</control>				
			</control>

            <control type="group">
                <posx>497</posx>
                <control type="image">
                    <include>Furniture_EpisodeMediaFlags</include>
                    <texture>flags/defaultscreen.png</texture>
                    <visible>!Control.IsVisible(187) + !Skin.HasSetting(nodefaultflags)</visible>
                </control>
                <control type="image" id="187">
                    <include>Furniture_EpisodeMediaFlags</include>
                    <texture>flags/sd.png</texture>
                    <visible>substring(listitem.director,sd)</visible>
                </control>
                <control type="image" id="187">
                    <include>Furniture_EpisodeMediaFlags</include>
                    <texture>flags/480p.png</texture>
                    <visible>substring(listitem.director,480p)</visible>
                </control>
                <control type="image" id="187">
                    <include>Furniture_EpisodeMediaFlags</include>
                    <texture>flags/custom/576p.png</texture>
                    <visible>substring(listitem.director,576p)</visible>
                </control>				
                <control type="image" id="187">
                    <include>Furniture_EpisodeMediaFlags</include>
                    <texture>flags/720p.png</texture>
                    <visible>substring(listitem.director,720p)</visible>
                </control>
                <control type="image" id="187">
                    <include>Furniture_EpisodeMediaFlags</include>
                    <texture>flags/1080p.png</texture>
                    <visible>substring(listitem.director,1080p)</visible>
                </control>
                <control type="image" id="187">
                    <include>Furniture_EpisodeMediaFlags</include>
                    <texture>flags/480i.png</texture>
                    <visible>substring(listitem.director,480i)</visible>
                </control>
                <control type="image" id="187">
                    <include>Furniture_EpisodeMediaFlags</include>
                    <texture>flags/576i.png</texture>
                    <visible>substring(listitem.director,576i)</visible>
                </control>				
                <control type="image" id="187">
                    <include>Furniture_EpisodeMediaFlags</include>
                    <texture>flags/720i.png</texture>
                    <visible>substring(listitem.director,720i)</visible>
                </control>
                <control type="image" id="187">
                    <include>Furniture_EpisodeMediaFlags</include>
                    <texture>flags/1080i.png</texture>
                    <visible>substring(listitem.director,1080i)</visible>
                </control>				
            </control>

			<control type="group">
				<posx>576</posx>
				<control type="image">
                    <include>Furniture_EpisodeMediaFlags</include>
                    <texture>flags/defaultsound.png</texture>
                    <visible>!Control.IsVisible(188) + !Skin.HasSetting(nodefaultflags)</visible>
                </control>					
				<control type="image" id="188">
					<include>Furniture_EpisodeMediaFlags</include>
					<texture>flags/custom/dtsma.png</texture>
					<visible>substring(listitem.director,dtsma) | substring(listitem.studio,master audio) + !substring(listitem.studio,ac-3)</visible>
				</control>					
				<control type="image" id="188">
					<include>Furniture_EpisodeMediaFlags</include>
					<texture>flags/dts.png</texture>
					<visible>substring(listitem.director,dts) + !substring(listitem.studio,ac-3) + !substring(listitem.studio,dtsma) | substring(listitem.studio,master audio)</visible>
				</control>			
				<control type="image" id="188">
					<include>Furniture_EpisodeMediaFlags</include>
					<texture>flags/custom/dolbytruehd.png</texture>
					<visible>substring(listitem.director,truehd) | substring(listitem.studio,true hd)</visible>
				</control>	
				<control type="image" id="188">
					<include>Furniture_EpisodeMediaFlags</include>
					<texture>flags/dolbydigital.png</texture>
					<visible>substring(listitem.director,ac-3)</visible>
				</control>
				<control type="image" id="188">
					<include>Furniture_EpisodeMediaFlags</include>
					<texture>flags/custom/mp3.png</texture>
					<visible>substring(listitem.director,MPEG Audio)</visible>
				</control>
				<control type="image" id="188">
					<include>Furniture_EpisodeMediaFlags</include>
					<texture>flags/custom/flac.png</texture>
					<visible>substring(listitem.director,flac)</visible>
				</control>
				<control type="image" id="188">
					<include>Furniture_EpisodeMediaFlags</include>
					<texture>flags/custom/ogg.png</texture>
					<visible>substring(listitem.director,vorbis)</visible>
				</control>				
				<control type="image" id="188">
					<include>Furniture_EpisodeMediaFlags</include>
					<texture>flags/custom/aac.png</texture>
					<visible>substring(listitem.director,aac)</visible>
				</control>				
            </control>
        </control>
    </include>
</includes>
</includes>